sbm69/__init__.py
sbm69/_structures.py
sbm69/cli.py
sbm69/connection.py
sbm69-0.4.1.dist-info/entry_points.txt
sbm69-0.4.1.dist-info/WHEEL
sbm69-0.4.1.dist-info/METADATA
sbm69-0.4.1.dist-info/RECORD
